README.rst
setup.py
chinadns/__init__.py
chinadns/dnsrelay.py
chinadns.egg-info/PKG-INFO
chinadns.egg-info/SOURCES.txt
chinadns.egg-info/dependency_links.txt
chinadns.egg-info/entry_points.txt
chinadns.egg-info/requires.txt
chinadns.egg-info/top_level.txt