Metadata-Version: 1.1
Name: chinadns
Version: 0.1.11
Summary: A DNS forwarder that ignore incorrect responses
Home-page: https://github.com/clowwindy/ChinaDNS
Author: clowwindy
Author-email: clowwindy42@gmail.com
License: MIT
Platform: UNKNOWN
Classifier: License :: OSI Approved :: MIT License
Classifier: Programming Language :: Python :: 2
Classifier: Programming Language :: Python :: 2.7
Classifier: Topic :: Internet :: Proxy Servers
